{
  "last_updated": "2026-05-16",
  "items": [
    {
      "id": "monkey-shoulder-whisky",
      "name": "Monkey Shoulder Blended Malt Scotch Whisky",
      "description": "Blended malt Scotch whisky. Smooth enough to drink neat, commonly used in cocktails.",
      "priority": "medium",
      "price_aud": 60,
      "retailers": [
        {
          "name": "Dan Murphy's",
          "url": "https://www.danmurphys.com.au/product/DM_375519/monkey-shoulder-blended-malt-scotch-whisky-700ml",
          "price_aud": 60,
          "perth_stores": true
        },
        {
          "name": "BWS",
          "url": "https://bws.com.au/product/375519/monkey-shoulder-blended-malt-scotch-whisky-700ml",
          "price_aud": 62,
          "perth_stores": true
        }
      ],
      "lead_time": "In stock",
      "perth_available": true,
      "added": "2026-05-16",
      "notes": "Price approximate (~$55–65) — check Dan Murphy's for current price. Any Perth Dan Murphy's or BWS will stock it. 700ml standard; 1L also available."
    },
    {
      "id": "moment-anamorphic-lens",
      "name": "Moment 1.33x Anamorphic Lens + Pixel 9 Pro Case",
      "description": "Nathan's taking a big trip and wants proper cinematic video on his phone. This is the lens that does it — widescreen 2.4:1 ratio with those horizontal lens flares you see in films. Heads up: this is two separate purchases. The lens is ~$250 and requires a specific Moment case for the Pixel 9 Pro (~$70) to mount properly — total around $320.",
      "priority": "high",
      "price_aud": 320,
      "retailers": [
        {
          "name": "Moment ANZ — Anamorphic 1.33x Lens (~$250)",
          "url": "https://shopmoment.au/collections/moment",
          "price_aud": 250,
          "perth_stores": false
        },
        {
          "name": "Moment ANZ — Pixel 9 Pro Case, required (~$70)",
          "url": "https://shopmoment.au/products/moment-case-for-pixel-9-pro-xl-compatible-with-magsafe",
          "price_aud": 70,
          "perth_stores": false
        }
      ],
      "lead_time": "Ships from Moment ANZ — typically 3–7 days to Perth",
      "perth_available": false,
      "added": "2026-05-16",
      "notes": "Gold or blue flare options — either is fine. Sirui is a quality alternative worth comparing. Both items ship from Moment's Australian store."
    },
    {
      "id": "magnetic-levitating-globe",
      "name": "Magnetic Levitating Globe with LED Light",
      "description": "Cool desk toy for Nathan's apartment — a globe that floats and spins above its base using magnets and lights up. Just something fun to have.",
      "priority": "low",
      "price_aud": 80,
      "retailers": [
        {
          "name": "Big W (in-store and online)",
          "url": "https://www.bigw.com.au/product/magnetic-levitating-floating-rotating-globe-with-touch-switches-led-light/p/9900084296",
          "price_aud": null,
          "perth_stores": true
        },
        {
          "name": "Kogan",
          "url": "https://www.kogan.com/au/buy/bostestore-magnetic-levitating-floating-rotating-globe-world-map-anti-gravity-6-inch-gift-f0185/",
          "price_aud": null,
          "perth_stores": false
        },
        {
          "name": "Amazon AU (browse options)",
          "url": "https://www.amazon.com.au/levitating-globe/s?k=levitating+globe",
          "price_aud": null,
          "perth_stores": false
        }
      ],
      "lead_time": "In stock online; Big W Perth stores likely stock these",
      "perth_available": true,
      "added": "2026-05-16",
      "notes": "Prices vary by size ($50–150). Go for a larger model (20cm+ globe) — the tiny 8cm ones are underwhelming. Check Big W first for easy in-person purchase."
    }
  ]
}
